helloworld.py
pingzee_gateway-0.0.1.dist-info/DESCRIPTION.rst
pingzee_gateway-0.0.1.dist-info/METADATA
pingzee_gateway-0.0.1.dist-info/RECORD
pingzee_gateway-0.0.1.dist-info/WHEEL
pingzee_gateway-0.0.1.dist-info/metadata.json
pingzee_gateway-0.0.1.dist-info/top_level.txt
